termrec/__init__.py
termrec/__main__.py
pytermrec-1.0.2.dist-info/LICENSE
pytermrec-1.0.2.dist-info/METADATA
pytermrec-1.0.2.dist-info/WHEEL
pytermrec-1.0.2.dist-info/entry_points.txt
pytermrec-1.0.2.dist-info/top_level.txt
pytermrec-1.0.2.dist-info/RECORD
