Metadata-Version: 2.1
Name: pytermrec
Version: 1.0.2
Summary: Record your terminal and play it
Home-page: https://github.com/donno2048/termrec
Author: Elisha Hollander
License: MIT
Platform: UNKNOWN
Classifier: Programming Language :: Python :: 3
License-File: LICENSE
Requires-Dist: questionary (>=1.10.0)
